[
  {
    "message": "Fault injection hardware..."
  },
  {
    "message": "# Start dez 18 20:17:16"
  },
  {
    "message": "1 ERRO: Falha ao obter TIME ou TIMER"
  },
  {
    "message": "2 ERRO: Falha ao obter TIME ou TIMER"
  },
  {
    "message": "3 ERRO: Falha ao obter TIME ou TIMER"
  },
  {
    "message": "4 ERRO: Falha ao obter TIME ou TIMER"
  },
  {
    "message": "5 ERRO: Falha ao obter TIME ou TIMER"
  },
  {
    "message": "6 ERRO: Falha ao obter TIME ou TIMER"
  },
  {
    "message": "7 ERRO: Falha ao obter TIME ou TIMER"
  },
  {
    "message": "8 ERRO: Falha ao obter TIME ou TIMER"
  },
  {
    "message": "9 ERRO: Falha ao obter TIME ou TIMER"
  },
  {
    "message": "10 ERRO: Falha ao obter TIME ou TIMER"
  },
  {
    "message": "11 ERRO: Falha ao obter TIME ou TIMER"
  },
  {
    "message": "12 ERRO: Falha ao obter TIME ou TIMER"
  },
  {
    "message": "13 ERRO: Falha ao obter TIME ou TIMER"
  },
  {
    "message": "14 ERRO: Falha ao obter TIME ou TIMER"
  },
  {
    "message": "15 ERRO: Falha ao obter TIME ou TIMER"
  },
  {
    "message": "16 ERRO: Falha ao obter TIME ou TIMER"
  },
  {
    "message": "17 ERRO: Falha ao obter TIME ou TIMER"
  },
  {
    "message": "18 ERRO: Falha ao obter TIME ou TIMER"
  },
  {
    "message": "19 ERRO: Falha ao obter TIME ou TIMER"
  },
  {
    "message": "20 ERRO: Falha ao obter TIME ou TIMER"
  },
  {
    "message": "21 ERRO: Falha ao obter TIME ou TIMER"
  },
  {
    "message": "22 ERRO: Falha ao obter TIME ou TIMER"
  },
  {
    "message": "23 ERRO: Falha ao obter TIME ou TIMER"
  },
  {
    "message": "24 ERRO: Falha ao obter TIME ou TIMER"
  },
  {
    "message": "25 ERRO: Falha ao obter TIME ou TIMER"
  },
  {
    "message": "26 ERRO: Falha ao obter TIME ou TIMER"
  },
  {
    "message": "27 ERRO: Falha ao obter TIME ou TIMER"
  },
  {
    "message": "28 ERRO: Falha ao obter TIME ou TIMER"
  },
  {
    "message": "29 ERRO: Falha ao obter TIME ou TIMER"
  },
  {
    "message": "30 ERRO: Falha ao obter TIME ou TIMER"
  },
  {
    "message": "31 ERRO: Falha ao obter TIME ou TIMER"
  },
  {
    "message": "32 ERRO: Falha ao obter TIME ou TIMER"
  },
  {
    "message": "33 ERRO: Falha ao obter TIME ou TIMER"
  },
  {
    "message": "34 ERRO: Falha ao obter TIME ou TIMER"
  },
  {
    "message": "35 ERRO: Falha ao obter TIME ou TIMER"
  },
  {
    "message": "36 ERRO: Falha ao obter TIME ou TIMER"
  },
  {
    "message": "37 ERRO: Falha ao obter TIME ou TIMER"
  },
  {
    "message": "38 ERRO: Falha ao obter TIME ou TIMER"
  },
  {
    "message": "39 ERRO: Falha ao obter TIME ou TIMER"
  },
  {
    "message": "40 ERRO: Falha ao obter TIME ou TIMER"
  },
  {
    "message": "41 ERRO: Falha ao obter TIME ou TIMER"
  },
  {
    "message": "42 ERRO: Falha ao obter TIME ou TIMER"
  },
  {
    "message": "43 ERRO: Falha ao obter TIME ou TIMER"
  },
  {
    "message": "44 ERRO: Falha ao obter TIME ou TIMER"
  },
  {
    "message": "45 ERRO: Falha ao obter TIME ou TIMER"
  },
  {
    "message": "46 ERRO: Falha ao obter TIME ou TIMER"
  },
  {
    "message": "47 ERRO: Falha ao obter TIME ou TIMER"
  },
  {
    "message": "48 ERRO: Falha ao obter TIME ou TIMER"
  },
  {
    "message": "49 ERRO: Falha ao obter TIME ou TIMER"
  },
  {
    "message": "50 ERRO: Falha ao obter TIME ou TIMER"
  },
  {
    "message": "End dez 18 20:17:20"
  }
]